fukui_net/__init__.py
fukui_net/cli.py
fukui_net/hf_integration.py
fukui_net/predictor.py
fukui_net/utils/__init__.py
fukui_net/utils/efficient_kan.py
fukui_net/utils/prepare.py
fukui_net/utils/train.py
fukui_net-0.1.1.dist-info/METADATA
fukui_net-0.1.1.dist-info/WHEEL
fukui_net-0.1.1.dist-info/entry_points.txt
fukui_net-0.1.1.dist-info/licenses/LICENSE
fukui_net-0.1.1.dist-info/RECORD
