Metadata-Version: 2.4
Name: fukui-net
Version: 0.1.1
Summary: A neural network for predicting Fukui indices using Kernel-based Attention Networks (KAN) with Chebyshev graph convolutions
Author-email: Sergei Nikolenko <sergei.nikolenko@gmail.com>
License: MIT
License-File: LICENSE
Keywords: DFT,biology,chemistry,fukui-indices,graph-neural-networks,molecular-property-prediction,pytorch,reactivity
Classifier: Development Status :: 4 - Beta
Classifier: Intended Audience :: Science/Research
Classifier: License :: OSI Approved :: MIT License
Classifier: Operating System :: OS Independent
Classifier: Programming Language :: Python :: 3
Classifier: Programming Language :: Python :: 3.11
Classifier: Programming Language :: Python :: 3.12
Classifier: Topic :: Scientific/Engineering :: Artificial Intelligence
Classifier: Topic :: Scientific/Engineering :: Chemistry
Requires-Python: >=3.11
Requires-Dist: huggingface-hub[cli]>=0.35.0
Requires-Dist: joblib>=1.5.2
Requires-Dist: lightning>=2.5.5
Requires-Dist: lion-pytorch>=0.2.3
Requires-Dist: numpy<2.0
Requires-Dist: pandas>=2.3.2
Requires-Dist: rdkit>=2022.9.5
Requires-Dist: rich>=14.1.0
Requires-Dist: scikit-learn>=1.7.2
Requires-Dist: torch-geometric>=2.6.1
Requires-Dist: torch>=2.8.0
Requires-Dist: transformers>=4.45.0
Requires-Dist: typer>=0.19.1
